elemi/__init__.py
elemi/elemi.py
elemi-0.1.0.dist-info/LICENSE
elemi-0.1.0.dist-info/METADATA
elemi-0.1.0.dist-info/WHEEL
elemi-0.1.0.dist-info/top_level.txt
elemi-0.1.0.dist-info/RECORD
