Metadata-Version: 2.1
Name: elemi
Version: 0.1.0
Summary: EleMi: Elastic Net Regularized Multi-Regression
Author-email: Nan Chen <nan.v.chen@gmail.com>
License: MIT License
Requires-Python: >=3.8
License-File: LICENSE
Requires-Dist: numpy>=1.21
